pyparadiseo-0.5.dist-info/LICENSE
pyparadiseo-0.5.dist-info/top_level.txt
pyparadiseo-0.5.dist-info/METADATA
pyparadiseo-0.5.dist-info/RECORD
pyparadiseo-0.5.dist-info/WHEEL
pyparadiseo.libs/libboost_numpy36-551a7a73.so.1.80.0
pyparadiseo.libs/libboost_python36-ae7c251c.so.1.80.0
pyparadiseo/_mod.so
pyparadiseo/swarm.py
pyparadiseo/solution.py
pyparadiseo/population.py
pyparadiseo/utils.py
pyparadiseo/operator.py
pyparadiseo/bounds.py
pyparadiseo/initializer.py
pyparadiseo/__init__.py
pyparadiseo/config.py
pyparadiseo/_core.so
pyparadiseo/evaluator.py
pyparadiseo/moeo/replacement.py
pyparadiseo/moeo/__init__.py
pyparadiseo/moeo/algo.py
pyparadiseo/moeo/fitness_assignment.py
pyparadiseo/moeo/diversity_assignment.py
pyparadiseo/mo/neighborhood.py
pyparadiseo/mo/sampling.py
pyparadiseo/mo/__init__.py
pyparadiseo/mo/algo.py
pyparadiseo/mo/comparator.py
pyparadiseo/mo/explorer.py
pyparadiseo/mo/eval.py
pyparadiseo/mo/continuator.py
pyparadiseo/eo/merge.py
pyparadiseo/eo/transform.py
pyparadiseo/eo/reduce.py
pyparadiseo/eo/stats.py
pyparadiseo/eo/breeders.py
pyparadiseo/eo/selector.py
pyparadiseo/eo/__init__.py
pyparadiseo/eo/algo.py
pyparadiseo/eo/replace.py
pyparadiseo/eo/select_one.py
pyparadiseo/eo/continuator.py
