Metadata-Version: 2.1
Name: pyparadiseo
Version: 0.5
Summary: Python version of the ParadisEO framework for metaheuristic optimization
Home-page: https://gitlab.inria.fr/paradiseo/pyparadiseo
Author: Jan Gmys
Author-email: jan.gmys@inria.fr
License: CeCILL
Platform: UNKNOWN
Requires-Python: >=3.6
Requires-Dist: numpy
Provides-Extra: test
Requires-Dist: pytest ; extra == 'test'
